pixel_clusterizer/__init__.py
pixel_clusterizer/cluster_functions.py
pixel_clusterizer/clusterizer.py
pixel_clusterizer-3.1.7.dist-info/LICENSE
pixel_clusterizer-3.1.7.dist-info/METADATA
pixel_clusterizer-3.1.7.dist-info/WHEEL
pixel_clusterizer-3.1.7.dist-info/top_level.txt
pixel_clusterizer-3.1.7.dist-info/RECORD
