Metadata-Version: 2.1
Name: pixel-clusterizer
Version: 3.1.7
Summary: A fast, generic, and easy to use clusterizer to cluster hits of a pixel matrix in Python.
Home-page: https://github.com/SiLab-Bonn/pixel_clusterizer
Author: Mark Standke, David-Leon Pohl, Jens Janssen
Author-email: dieter@physik.uni-bonn.de, pohl@physik.uni-bonn.de, janssen@physik.uni-bonn.de
Maintainer: Mark Standke, David-Leon Pohl, Jens Janssen
Maintainer-email: dieter@physik.uni-bonn.de, pohl@physik.uni-bonn.de, janssen@physik.uni-bonn.de
License: GNU LESSER GENERAL PUBLIC LICENSE Version 2.1
Keywords: cluster,clusterizer,pixel
Platform: any
Requires-Python: >=3.7
License-File: LICENSE
Requires-Dist: numpy
Requires-Dist: numba (>=0.24.0)
